replacer.py
replacer-1.1.1.dist-info/DESCRIPTION.rst
replacer-1.1.1.dist-info/METADATA
replacer-1.1.1.dist-info/RECORD
replacer-1.1.1.dist-info/WHEEL
replacer-1.1.1.dist-info/entry_points.txt
replacer-1.1.1.dist-info/metadata.json
replacer-1.1.1.dist-info/top_level.txt
