Metadata-Version: 2.0
Name: replacer
Version: 1.1.1
Summary: Replace text in files
Home-page: http://github.com/dmerejkowsky/replacer
Author: Dimitri Merejkowky
Author-email: d.merej@gmail.com
License: BSD
Platform: UNKNOWN
Classifier: Environment :: Console
Classifier: License :: OSI Approved :: BSD License
Classifier: Programming Language :: Python
Classifier: Topic :: System :: Shells
